evrmore_authentication/__init__.py
evrmore_authentication/api.py
evrmore_authentication/auth.py
evrmore_authentication/crypto.py
evrmore_authentication/dependencies.py
evrmore_authentication/exceptions.py
evrmore_authentication/manual_test.py
evrmore_authentication/models.py
evrmore_authentication/setup.py
evrmore_authentication/bin/__init__.py
evrmore_authentication/bin/api_server.py
scripts/__init__.py
scripts/run_api_server.py
scripts/run_web_demo.py
evrmore_authentication-0.3.0.dist-info/LICENSE
evrmore_authentication-0.3.0.dist-info/METADATA
evrmore_authentication-0.3.0.dist-info/WHEEL
evrmore_authentication-0.3.0.dist-info/entry_points.txt
evrmore_authentication-0.3.0.dist-info/top_level.txt
evrmore_authentication-0.3.0.dist-info/RECORD
