Metadata-Version: 2.2
Name: evrmore-authentication
Version: 0.3.0
Summary: Authentication system using Evrmore blockchain signatures
Home-page: https://github.com/manticoretechnologies/evrmore-authentication
Author: Manticore Technologies
Author-email: dev@manticore.technology
Project-URL: Documentation, https://manticoretechnologies.github.io/evrmore-authentication/
Project-URL: Bug Tracker, https://github.com/manticoretechnologies/evrmore-authentication/issues
Classifier: Programming Language :: Python :: 3
Classifier: License :: OSI Approved :: MIT License
Classifier: Operating System :: OS Independent
Classifier: Development Status :: 4 - Beta
Classifier: Intended Audience :: Developers
Classifier: Topic :: Security :: Cryptography
Requires-Python: >=3.7
License-File: LICENSE
Requires-Dist: coincurve>=17.0.0
Requires-Dist: pycryptodome>=3.15.0
Requires-Dist: base58>=2.1.0
Requires-Dist: pyjwt>=2.3.0
Requires-Dist: cryptography>=36.0.0
Requires-Dist: fastapi>=0.75.0
Requires-Dist: uvicorn>=0.17.0
Requires-Dist: python-dotenv>=0.19.0
Requires-Dist: pydantic>=1.9.0
Dynamic: author
Dynamic: author-email
Dynamic: classifier
Dynamic: description
Dynamic: description-content-type
Dynamic: home-page
Dynamic: project-url
Dynamic: requires-dist
Dynamic: requires-python
Dynamic: summary
